mylib_037/__init__.py
mylib_037-0.1.dist-info/LICENSE.txt
mylib_037-0.1.dist-info/METADATA
mylib_037-0.1.dist-info/WHEEL
mylib_037-0.1.dist-info/top_level.txt
mylib_037-0.1.dist-info/RECORD
