Metadata-Version: 2.1
Name: mylib-037
Version: 0.1
Summary: for calculating square
Author: Shivam
Author-email: shivamsharma2111.ss@gmail.com
Classifier: Programming Language :: Python :: 3
Classifier: License :: OSI Approved :: MIT License
Classifier: Operating System :: OS Independent
License-File: LICENSE.txt
